apiosintDS/__init__.py
apiosintDS/apiosintDS.py
apiosintDS/modules/__init__.py
apiosintDS/modules/dosearch.py
apiosintDS/modules/listutils.py
apiosintDS/modules/scriptinfo.py
apiosintDS/modules/stixreport.py
apiosintDS/schema/schema.json
apiosintDS/utilities/__init__.py
apiosintDS/utilities/logutils.py
apiosintDS/utilities/prettycli.py
apiosintDS-2.0.2.dist-info/LICENSE.txt
apiosintDS-2.0.2.dist-info/METADATA
apiosintDS-2.0.2.dist-info/WHEEL
apiosintDS-2.0.2.dist-info/entry_points.txt
apiosintDS-2.0.2.dist-info/top_level.txt
apiosintDS-2.0.2.dist-info/RECORD
