Metadata-Version: 2.1
Name: apiosintDS
Version: 2.0.2
Summary: On demand query API for OSINT.digitalside.it project. You can query for souspicious domains, urls, IPv4 and file hashes.
Home-page: https://github.com/davidonzo/apiosintDS
Author: Davide Baglieri
Author-email: info@digitalside.it
License: MIT
Keywords: apiosintDS,OSINT,Threat-Intel,IoC,Security
Classifier: Development Status :: 4 - Beta
Classifier: Intended Audience :: Information Technology
Classifier: Topic :: Security
Classifier: License :: OSI Approved :: MIT License
Classifier: Programming Language :: Python :: 3
Requires-Python: >3.5.2
License-File: LICENSE.txt
Requires-Dist: pytz ==2023.3
Requires-Dist: requests
Requires-Dist: urllib3
Requires-Dist: stix2
